odoo/addons/web_group_by_percentage/README.rst
odoo/addons/web_group_by_percentage/__init__.py
odoo/addons/web_group_by_percentage/__manifest__.py
odoo/addons/web_group_by_percentage/i18n/ca.po
odoo/addons/web_group_by_percentage/i18n/es.po
odoo/addons/web_group_by_percentage/i18n/it.po
odoo/addons/web_group_by_percentage/i18n/pt_BR.po
odoo/addons/web_group_by_percentage/i18n/web_group_by_percentage.pot
odoo/addons/web_group_by_percentage/i18n/zh_CN.po
odoo/addons/web_group_by_percentage/readme/CONTRIBUTORS.rst
odoo/addons/web_group_by_percentage/readme/DESCRIPTION.rst
odoo/addons/web_group_by_percentage/readme/USAGE.rst
odoo/addons/web_group_by_percentage/static/description/icon.png
odoo/addons/web_group_by_percentage/static/description/index.html
odoo/addons/web_group_by_percentage/static/description/screenshot.png
odoo/addons/web_group_by_percentage/static/src/js/backend.esm.js
odoo/addons/web_group_by_percentage/static/src/legacy/js/backend_legacy.js
odoo/addons/web_group_by_percentage/static/src/scss/backend.scss
odoo/addons/web_group_by_percentage/static/src/xml/list_grouprow_percentage.xml
odoo_addon_web_group_by_percentage-16.0.1.0.0.7.dist-info/METADATA
odoo_addon_web_group_by_percentage-16.0.1.0.0.7.dist-info/WHEEL
odoo_addon_web_group_by_percentage-16.0.1.0.0.7.dist-info/top_level.txt
odoo_addon_web_group_by_percentage-16.0.1.0.0.7.dist-info/RECORD
